elims/__init__.py
elims/elims.py
elims/py.typed
elims-0.0.1.dist-info/WHEEL
elims-0.0.1.dist-info/METADATA
elims-0.0.1.dist-info/RECORD
