Metadata-Version: 2.3
Name: elims
Version: 0.0.1
Summary: Electronic Laboratory Information Management System
Keywords: laboratory,information,management,system,lims
Author: Fabien Meyer
Author-email: Fabien Meyer <fabien.meyer@outlook.com>
License: MIT
Classifier: Development Status :: 3 - Alpha
Classifier: Intended Audience :: Science/Research
Classifier: License :: OSI Approved :: MIT License
Classifier: Operating System :: OS Independent
Classifier: Programming Language :: Python :: 3
Classifier: Programming Language :: Python :: 3.13
Classifier: Topic :: Scientific/Engineering
Requires-Dist: pydantic-settings>=2.11.0
Requires-Dist: sqlmodel>=0.0.27
Requires-Python: >=3.13
